{
  "students": [
    {
      "firstName": "Patrick",
      "lastName": "Student",
      "id": 2
    },
    {
      "id": 3,
      "firstName": "Bob",
      "lastName": "Pant"
    },
    {
      "id": 4,
      "firstName": "Artur",
      "lastName": "Nitsevich"
    }
  ],
  "subjects": [
    {
      "id": 1,
      "name": "Math"
    },
    {
      "id": 2,
      "name": "History"
    },
    {
      "id": 4,
      "name": "IT"
    },
    {
      "id": 5,
      "name": "Subject🍖"
    }
  ],
  "sessions": [
    {
      "id": 1,
      "studentId": 3,
      "subjectId": 1
    },
    {
      "id": 3,
      "studentId": 2,
      "subjectId": 4
    },
    {
      "id": 4,
      "studentId": 3,
      "subjectId": 5
    }
  ]
}